multiline_formatter/__init__.py
multiline_formatter/formatter.py
multiline_log_formatter-0.1.8.dist-info/DESCRIPTION.rst
multiline_log_formatter-0.1.8.dist-info/METADATA
multiline_log_formatter-0.1.8.dist-info/metadata.json
multiline_log_formatter-0.1.8.dist-info/RECORD
multiline_log_formatter-0.1.8.dist-info/top_level.txt
multiline_log_formatter-0.1.8.dist-info/WHEEL
