Metadata-Version: 2.0
Name: multiline-log-formatter
Version: 0.1.8
Summary: Python logging formatter that prefix multiline log message and trackebacks.
Home-page: https://github.com/peterlauri/python-multiline-log-formatter
Author: Peter Lauri
Author-email: peterlauri@gmail.com
License: BSD
Keywords: logs,logging
Platform: UNKNOWN
Classifier: Development Status :: 5 - Production/Stable
Classifier: Intended Audience :: Developers
Classifier: License :: OSI Approved :: BSD License
Classifier: Operating System :: Unix
Classifier: Operating System :: POSIX
Classifier: Operating System :: Microsoft :: Windows
Classifier: Programming Language :: Python
Classifier: Programming Language :: Python :: 2.7
Classifier: Programming Language :: Python :: 3
Classifier: Programming Language :: Python :: 3.3
Classifier: Programming Language :: Python :: 3.4
Classifier: Programming Language :: Python :: 3.5
Classifier: Programming Language :: Python :: Implementation :: CPython
Classifier: Programming Language :: Python :: Implementation :: PyPy
Classifier: Topic :: Utilities
